Lifetime/__init__.py
Signals/SignalHandler.py
Signals/Signals.py
Signals/WinSignalHandler.py
Signals/__init__.py
Signals/threads.py
ZServer/AccessLogger.py
ZServer/BaseLogger.py
ZServer/ClockServer.py
ZServer/DebugLogger.py
ZServer/FCGIServer.py
ZServer/FTPRequest.py
ZServer/FTPResponse.py
ZServer/FTPServer.py
ZServer/HTTPResponse.py
ZServer/HTTPServer.py
ZServer/ICPServer.py
ZServer/PCGIServer.py
ZServer/Producers.py
ZServer/README.txt
ZServer/WebDAVSrcHandler.py
ZServer/__init__.py
ZServer/component.xml
ZServer/datatypes.py
ZServer/utils.py
ZServer/PubCore/ZEvent.py
ZServer/PubCore/ZRendezvous.py
ZServer/PubCore/ZServerPublisher.py
ZServer/PubCore/__init__.py
ZServer/Testing/__init__.py
ZServer/Testing/doctest_functional.py
ZServer/Testing/functional.py
ZServer/Testing/threadutils.py
ZServer/Testing/utils.py
ZServer/ZPublisher/Publish.py
ZServer/ZPublisher/__init__.py
ZServer/ZPublisher/exceptionhook.py
ZServer/ZPublisher/xmlrpc.py
ZServer/ZPublisher/tests/__init__.py
ZServer/ZPublisher/tests/test_exceptionhook.py
ZServer/ZPublisher/tests/test_pubevents.py
ZServer/ZPublisher/tests/test_publish.py
ZServer/Zope2/__init__.py
ZServer/Zope2/App/__init__.py
ZServer/Zope2/App/tests/__init__.py
ZServer/Zope2/App/tests/test_schema.py
ZServer/Zope2/Startup/__init__.py
ZServer/Zope2/Startup/config.py
ZServer/Zope2/Startup/datatypes.py
ZServer/Zope2/Startup/handlers.py
ZServer/Zope2/Startup/options.py
ZServer/Zope2/Startup/run.py
ZServer/Zope2/Startup/starter.py
ZServer/Zope2/Startup/utils.py
ZServer/Zope2/Startup/warnfilter.py
ZServer/Zope2/Startup/warnfilter.xml
ZServer/Zope2/Startup/zopectl.py
ZServer/Zope2/Startup/zopeschema.xml
ZServer/Zope2/Startup/tests/__init__.py
ZServer/Zope2/Startup/tests/testStarter.py
ZServer/Zope2/Startup/tests/test_schema.py
ZServer/Zope2/Startup/tests/test_warnfilter.py
ZServer/Zope2/utilities/__init__.py
ZServer/Zope2/utilities/copyzopeskel.py
ZServer/Zope2/utilities/mkzopeinstance.py
ZServer/Zope2/utilities/zpasswd.py
ZServer-4.0.2.dist-info/LICENSE.txt
ZServer-4.0.2.dist-info/METADATA
ZServer-4.0.2.dist-info/WHEEL
ZServer-4.0.2.dist-info/entry_points.txt
ZServer-4.0.2.dist-info/top_level.txt
ZServer-4.0.2.dist-info/RECORD
