Metadata-Version: 2.1
Name: ZServer
Version: 4.0.2
Summary: Zope ZServer.
Home-page: https://github.com/zopefoundation/ZServer
Author: Zope Foundation and Contributors
Author-email: zope-dev@zope.org
License: ZPL 2.1
Platform: UNKNOWN
Classifier: Development Status :: 6 - Mature
Classifier: Environment :: Web Environment
Classifier: Framework :: Zope
Classifier: Framework :: Zope :: 4
Classifier: License :: OSI Approved :: Zope Public License
Classifier: Operating System :: OS Independent
Classifier: Programming Language :: Python
Classifier: Programming Language :: Python :: 2 :: Only
Classifier: Programming Language :: Python :: 2.7
Classifier: Programming Language :: Python :: Implementation :: CPython
Requires-Dist: setuptools
Requires-Dist: AccessControl
Requires-Dist: Acquisition
Requires-Dist: ExtensionClass
Requires-Dist: Persistence
Requires-Dist: transaction
Requires-Dist: ZConfig
Requires-Dist: zdaemon
Requires-Dist: zExceptions
Requires-Dist: ZODB
Requires-Dist: zope.component
Requires-Dist: zope.container
Requires-Dist: zope.contenttype
Requires-Dist: zope.deferredimport
Requires-Dist: zope.event
Requires-Dist: zope.interface
Requires-Dist: zope.lifecycleevent
Requires-Dist: zope.processlifetime
Requires-Dist: zope.schema
Requires-Dist: zope.testing
Requires-Dist: Zope (>=4.0b6)
Provides-Extra: sdnotify
Requires-Dist: sdnotify ; extra == 'sdnotify'
